{
    "apiVersion": "v1",
    "items": [
        {
            "apiVersion": "v1",
            "kind": "Pod",
            "metadata": {
                "creationTimestamp": "2022-05-16T22:12:23Z",
                "generateName": "parsec-blackscholes-",
                "labels": {
                    "controller-uid": "2caae87c-600d-482e-9c2d-bde230409d82",
                    "job-name": "parsec-blackscholes"
                },
                "managedFields": [
                    {
                        "apiVersion": "v1",
                        "fieldsType": "FieldsV1",
                        "fieldsV1": {
                            "f:metadata": {
                                "f:generateName": {},
                                "f:labels": {
                                    ".": {},
                                    "f:controller-uid": {},
                                    "f:job-name": {}
                                },
                                "f:ownerReferences": {
                                    ".": {},
                                    "k:{\"uid\":\"2caae87c-600d-482e-9c2d-bde230409d82\"}": {
                                        ".": {},
                                        "f:apiVersion": {},
                                        "f:blockOwnerDeletion": {},
                                        "f:controller": {},
                                        "f:kind": {},
                                        "f:name": {},
                                        "f:uid": {}
                                    }
                                }
                            },
                            "f:spec": {
                                "f:containers": {
                                    "k:{\"name\":\"parsecblackscholes\"}": {
                                        ".": {},
                                        "f:args": {},
                                        "f:command": {},
                                        "f:image": {},
                                        "f:imagePullPolicy": {},
                                        "f:name": {},
                                        "f:resources": {
                                            ".": {},
                                            "f:limits": {
                                                ".": {},
                                                "f:cpu": {}
                                            },
                                            "f:requests": {
                                                ".": {},
                                                "f:cpu": {}
                                            }
                                        },
                                        "f:terminationMessagePath": {},
                                        "f:terminationMessagePolicy": {}
                                    }
                                },
                                "f:dnsPolicy": {},
                                "f:enableServiceLinks": {},
                                "f:nodeSelector": {
                                    ".": {},
                                    "f:cca-project-nodetype": {}
                                },
                                "f:restartPolicy": {},
                                "f:schedulerName": {},
                                "f:securityContext": {},
                                "f:terminationGracePeriodSeconds": {}
                            }
                        },
                        "manager": "kube-controller-manager",
                        "operation": "Update",
                        "time": "2022-05-16T22:12:23Z"
                    },
                    {
                        "apiVersion": "v1",
                        "fieldsType": "FieldsV1",
                        "fieldsV1": {
                            "f:status": {
                                "f:conditions": {
                                    ".": {},
                                    "k:{\"type\":\"PodScheduled\"}": {
                                        ".": {},
                                        "f:lastProbeTime": {},
                                        "f:lastTransitionTime": {},
                                        "f:message": {},
                                        "f:reason": {},
                                        "f:status": {},
                                        "f:type": {}
                                    }
                                }
                            }
                        },
                        "manager": "kube-scheduler",
                        "operation": "Update",
                        "time": "2022-05-16T22:12:23Z"
                    },
                    {
                        "apiVersion": "v1",
                        "fieldsType": "FieldsV1",
                        "fieldsV1": {
                            "f:status": {
                                "f:conditions": {
                                    "k:{\"type\":\"ContainersReady\"}": {
                                        ".": {},
                                        "f:lastProbeTime": {},
                                        "f:lastTransitionTime": {},
                                        "f:reason": {},
                                        "f:status": {},
                                        "f:type": {}
                                    },
                                    "k:{\"type\":\"Initialized\"}": {
                                        ".": {},
                                        "f:lastProbeTime": {},
                                        "f:lastTransitionTime": {},
                                        "f:reason": {},
                                        "f:status": {},
                                        "f:type": {}
                                    },
                                    "k:{\"type\":\"Ready\"}": {
                                        ".": {},
                                        "f:lastProbeTime": {},
                                        "f:lastTransitionTime": {},
                                        "f:reason": {},
                                        "f:status": {},
                                        "f:type": {}
                                    }
                                },
                                "f:containerStatuses": {},
                                "f:hostIP": {},
                                "f:phase": {},
                                "f:podIP": {},
                                "f:podIPs": {
                                    ".": {},
                                    "k:{\"ip\":\"100.96.3.23\"}": {
                                        ".": {},
                                        "f:ip": {}
                                    }
                                },
                                "f:startTime": {}
                            }
                        },
                        "manager": "kubelet",
                        "operation": "Update",
                        "time": "2022-05-16T22:15:17Z"
                    }
                ],
                "name": "parsec-blackscholes-9kldc",
                "namespace": "default",
                "ownerReferences": [
                    {
                        "apiVersion": "batch/v1",
                        "blockOwnerDeletion": true,
                        "controller": true,
                        "kind": "Job",
                        "name": "parsec-blackscholes",
                        "uid": "2caae87c-600d-482e-9c2d-bde230409d82"
                    }
                ],
                "resourceVersion": "11058",
                "selfLink": "/api/v1/namespaces/default/pods/parsec-blackscholes-9kldc",
                "uid": "ea724ee6-05b0-4fb9-a2b8-993e735054ca"
            },
            "spec": {
                "containers": [
                    {
                        "args": [
                            "-c",
                            "taskset -c 3-7  ./bin/parsecmgmt -a run -p blackscholes -i native -n 5"
                        ],
                        "command": [
                            "/bin/sh"
                        ],
                        "image": "anakli/parsec:blackscholes-native-reduced",
                        "imagePullPolicy": "Always",
                        "name": "parsecblackscholes",
                        "resources": {
                            "limits": {
                                "cpu": "5"
                            },
                            "requests": {
                                "cpu": "5"
                            }
                        },
                        "terminationMessagePath": "/dev/termination-log",
                        "terminationMessagePolicy": "File",
                        "volumeMounts": [
                            {
                                "mountPath": "/var/run/secrets/kubernetes.io/serviceaccount",
                                "name": "default-token-qxwdw",
                                "readOnly": true
                            }
                        ]
                    }
                ],
                "dnsPolicy": "ClusterFirst",
                "enableServiceLinks": true,
                "nodeName": "node-c-8core-g1vx",
                "nodeSelector": {
                    "cca-project-nodetype": "node-c-8core"
                },
                "preemptionPolicy": "PreemptLowerPriority",
                "priority": 0,
                "restartPolicy": "Never",
                "schedulerName": "default-scheduler",
                "securityContext": {},
                "serviceAccount": "default",
                "serviceAccountName": "default",
                "terminationGracePeriodSeconds": 30,
                "tolerations": [
                    {
                        "effect": "NoExecute",
                        "key": "node.kubernetes.io/not-ready",
                        "operator": "Exists",
                        "tolerationSeconds": 300
                    },
                    {
                        "effect": "NoExecute",
                        "key": "node.kubernetes.io/unreachable",
                        "operator": "Exists",
                        "tolerationSeconds": 300
                    }
                ],
                "volumes": [
                    {
                        "name": "default-token-qxwdw",
                        "secret": {
                            "defaultMode": 420,
                            "secretName": "default-token-qxwdw"
                        }
                    }
                ]
            },
            "status": {
                "conditions": [
                    {
                        "lastProbeTime": null,
                        "lastTransitionTime": "2022-05-16T22:13:46Z",
                        "reason": "PodCompleted",
                        "status": "True",
                        "type": "Initialized"
                    },
                    {
                        "lastProbeTime": null,
                        "lastTransitionTime": "2022-05-16T22:15:17Z",
                        "reason": "PodCompleted",
                        "status": "False",
                        "type": "Ready"
                    },
                    {
                        "lastProbeTime": null,
                        "lastTransitionTime": "2022-05-16T22:15:17Z",
                        "reason": "PodCompleted",
                        "status": "False",
                        "type": "ContainersReady"
                    },
                    {
                        "lastProbeTime": null,
                        "lastTransitionTime": "2022-05-16T22:13:46Z",
                        "status": "True",
                        "type": "PodScheduled"
                    }
                ],
                "containerStatuses": [
                    {
                        "containerID": "docker://bd2575ada89035a8ca49a169a35c7206fbafe61f9191c7b5f5595400f9cdee0e",
                        "image": "anakli/parsec:blackscholes-native-reduced",
                        "imageID": "docker-pullable://anakli/parsec@sha256:09493daac822c3ba0889a5ae0aad6c6792aedf6b077d4352d103e2a0e3e50063",
                        "lastState": {},
                        "name": "parsecblackscholes",
                        "ready": false,
                        "restartCount": 0,
                        "started": false,
                        "state": {
                            "terminated": {
                                "containerID": "docker://bd2575ada89035a8ca49a169a35c7206fbafe61f9191c7b5f5595400f9cdee0e",
                                "exitCode": 0,
                                "finishedAt": "2022-05-16T22:15:15Z",
                                "reason": "Completed",
                                "startedAt": "2022-05-16T22:13:48Z"
                            }
                        }
                    }
                ],
                "hostIP": "10.156.15.227",
                "phase": "Succeeded",
                "podIP": "100.96.3.23",
                "podIPs": [
                    {
                        "ip": "100.96.3.23"
                    }
                ],
                "qosClass": "Burstable",
                "startTime": "2022-05-16T22:13:46Z"
            }
        },
        {
            "apiVersion": "v1",
            "kind": "Pod",
            "metadata": {
                "creationTimestamp": "2022-05-16T22:10:22Z",
                "generateName": "parsec-canneal-",
                "labels": {
                    "controller-uid": "130409cf-05df-4bca-8a5a-51a87b6d1a6a",
                    "job-name": "parsec-canneal"
                },
                "managedFields": [
                    {
                        "apiVersion": "v1",
                        "fieldsType": "FieldsV1",
                        "fieldsV1": {
                            "f:metadata": {
                                "f:generateName": {},
                                "f:labels": {
                                    ".": {},
                                    "f:controller-uid": {},
                                    "f:job-name": {}
                                },
                                "f:ownerReferences": {
                                    ".": {},
                                    "k:{\"uid\":\"130409cf-05df-4bca-8a5a-51a87b6d1a6a\"}": {
                                        ".": {},
                                        "f:apiVersion": {},
                                        "f:blockOwnerDeletion": {},
                                        "f:controller": {},
                                        "f:kind": {},
                                        "f:name": {},
                                        "f:uid": {}
                                    }
                                }
                            },
                            "f:spec": {
                                "f:containers": {
                                    "k:{\"name\":\"parseccanneal\"}": {
                                        ".": {},
                                        "f:args": {},
                                        "f:command": {},
                                        "f:image": {},
                                        "f:imagePullPolicy": {},
                                        "f:name": {},
                                        "f:resources": {
                                            ".": {},
                                            "f:limits": {
                                                ".": {},
                                                "f:cpu": {}
                                            },
                                            "f:requests": {
                                                ".": {},
                                                "f:cpu": {}
                                            }
                                        },
                                        "f:terminationMessagePath": {},
                                        "f:terminationMessagePolicy": {}
                                    }
                                },
                                "f:dnsPolicy": {},
                                "f:enableServiceLinks": {},
                                "f:nodeSelector": {
                                    ".": {},
                                    "f:cca-project-nodetype": {}
                                },
                                "f:restartPolicy": {},
                                "f:schedulerName": {},
                                "f:securityContext": {},
                                "f:terminationGracePeriodSeconds": {}
                            }
                        },
                        "manager": "kube-controller-manager",
                        "operation": "Update",
                        "time": "2022-05-16T22:10:22Z"
                    },
                    {
                        "apiVersion": "v1",
                        "fieldsType": "FieldsV1",
                        "fieldsV1": {
                            "f:status": {
                                "f:conditions": {
                                    "k:{\"type\":\"ContainersReady\"}": {
                                        ".": {},
                                        "f:lastProbeTime": {},
                                        "f:lastTransitionTime": {},
                                        "f:reason": {},
                                        "f:status": {},
                                        "f:type": {}
                                    },
                                    "k:{\"type\":\"Initialized\"}": {
                                        ".": {},
                                        "f:lastProbeTime": {},
                                        "f:lastTransitionTime": {},
                                        "f:reason": {},
                                        "f:status": {},
                                        "f:type": {}
                                    },
                                    "k:{\"type\":\"Ready\"}": {
                                        ".": {},
                                        "f:lastProbeTime": {},
                                        "f:lastTransitionTime": {},
                                        "f:reason": {},
                                        "f:status": {},
                                        "f:type": {}
                                    }
                                },
                                "f:containerStatuses": {},
                                "f:hostIP": {},
                                "f:phase": {},
                                "f:podIP": {},
                                "f:podIPs": {
                                    ".": {},
                                    "k:{\"ip\":\"100.96.3.22\"}": {
                                        ".": {},
                                        "f:ip": {}
                                    }
                                },
                                "f:startTime": {}
                            }
                        },
                        "manager": "kubelet",
                        "operation": "Update",
                        "time": "2022-05-16T22:13:46Z"
                    }
                ],
                "name": "parsec-canneal-fshtq",
                "namespace": "default",
                "ownerReferences": [
                    {
                        "apiVersion": "batch/v1",
                        "blockOwnerDeletion": true,
                        "controller": true,
                        "kind": "Job",
                        "name": "parsec-canneal",
                        "uid": "130409cf-05df-4bca-8a5a-51a87b6d1a6a"
                    }
                ],
                "resourceVersion": "10749",
                "selfLink": "/api/v1/namespaces/default/pods/parsec-canneal-fshtq",
                "uid": "b9cfbddb-80b1-4c50-b65b-45b6d5bd2d99"
            },
            "spec": {
                "containers": [
                    {
                        "args": [
                            "-c",
                            "taskset -c 0-2 ./bin/parsecmgmt -a run -p canneal -i native -n 3"
                        ],
                        "command": [
                            "/bin/sh"
                        ],
                        "image": "anakli/parsec:canneal-native-reduced",
                        "imagePullPolicy": "Always",
                        "name": "parseccanneal",
                        "resources": {
                            "limits": {
                                "cpu": "3"
                            },
                            "requests": {
                                "cpu": "3"
                            }
                        },
                        "terminationMessagePath": "/dev/termination-log",
                        "terminationMessagePolicy": "File",
                        "volumeMounts": [
                            {
                                "mountPath": "/var/run/secrets/kubernetes.io/serviceaccount",
                                "name": "default-token-qxwdw",
                                "readOnly": true
                            }
                        ]
                    }
                ],
                "dnsPolicy": "ClusterFirst",
                "enableServiceLinks": true,
                "nodeName": "node-c-8core-g1vx",
                "nodeSelector": {
                    "cca-project-nodetype": "node-c-8core"
                },
                "preemptionPolicy": "PreemptLowerPriority",
                "priority": 0,
                "restartPolicy": "Never",
                "schedulerName": "default-scheduler",
                "securityContext": {},
                "serviceAccount": "default",
                "serviceAccountName": "default",
                "terminationGracePeriodSeconds": 30,
                "tolerations": [
                    {
                        "effect": "NoExecute",
                        "key": "node.kubernetes.io/not-ready",
                        "operator": "Exists",
                        "tolerationSeconds": 300
                    },
                    {
                        "effect": "NoExecute",
                        "key": "node.kubernetes.io/unreachable",
                        "operator": "Exists",
                        "tolerationSeconds": 300
                    }
                ],
                "volumes": [
                    {
                        "name": "default-token-qxwdw",
                        "secret": {
                            "defaultMode": 420,
                            "secretName": "default-token-qxwdw"
                        }
                    }
                ]
            },
            "status": {
                "conditions": [
                    {
                        "lastProbeTime": null,
                        "lastTransitionTime": "2022-05-16T22:10:22Z",
                        "reason": "PodCompleted",
                        "status": "True",
                        "type": "Initialized"
                    },
                    {
                        "lastProbeTime": null,
                        "lastTransitionTime": "2022-05-16T22:13:46Z",
                        "reason": "PodCompleted",
                        "status": "False",
                        "type": "Ready"
                    },
                    {
                        "lastProbeTime": null,
                        "lastTransitionTime": "2022-05-16T22:13:46Z",
                        "reason": "PodCompleted",
                        "status": "False",
                        "type": "ContainersReady"
                    },
                    {
                        "lastProbeTime": null,
                        "lastTransitionTime": "2022-05-16T22:10:22Z",
                        "status": "True",
                        "type": "PodScheduled"
                    }
                ],
                "containerStatuses": [
                    {
                        "containerID": "docker://6d443412bd63d62d21e0dce2d5fbf5d6e393e19843b3e89f845757863fe5e8ac",
                        "image": "anakli/parsec:canneal-native-reduced",
                        "imageID": "docker-pullable://anakli/parsec@sha256:1fa2a7c6e4dd08b8636c4a56042f3f46679f0fdba28f69574524b2ebd54a8941",
                        "lastState": {},
                        "name": "parseccanneal",
                        "ready": false,
                        "restartCount": 0,
                        "started": false,
                        "state": {
                            "terminated": {
                                "containerID": "docker://6d443412bd63d62d21e0dce2d5fbf5d6e393e19843b3e89f845757863fe5e8ac",
                                "exitCode": 0,
                                "finishedAt": "2022-05-16T22:13:45Z",
                                "reason": "Completed",
                                "startedAt": "2022-05-16T22:10:24Z"
                            }
                        }
                    }
                ],
                "hostIP": "10.156.15.227",
                "phase": "Succeeded",
                "podIP": "100.96.3.22",
                "podIPs": [
                    {
                        "ip": "100.96.3.22"
                    }
                ],
                "qosClass": "Burstable",
                "startTime": "2022-05-16T22:10:22Z"
            }
        },
        {
            "apiVersion": "v1",
            "kind": "Pod",
            "metadata": {
                "annotations": {
                    "kubernetes.io/limit-ranger": "LimitRanger plugin set: cpu request for container parsecdedup"
                },
                "creationTimestamp": "2022-05-16T22:13:21Z",
                "generateName": "parsec-dedup-",
                "labels": {
                    "controller-uid": "2a900972-37ae-49e2-a7be-f1d9edbda185",
                    "job-name": "parsec-dedup"
                },
                "managedFields": [
                    {
                        "apiVersion": "v1",
                        "fieldsType": "FieldsV1",
                        "fieldsV1": {
                            "f:metadata": {
                                "f:generateName": {},
                                "f:labels": {
                                    ".": {},
                                    "f:controller-uid": {},
                                    "f:job-name": {}
                                },
                                "f:ownerReferences": {
                                    ".": {},
                                    "k:{\"uid\":\"2a900972-37ae-49e2-a7be-f1d9edbda185\"}": {
                                        ".": {},
                                        "f:apiVersion": {},
                                        "f:blockOwnerDeletion": {},
                                        "f:controller": {},
                                        "f:kind": {},
                                        "f:name": {},
                                        "f:uid": {}
                                    }
                                }
                            },
                            "f:spec": {
                                "f:containers": {
                                    "k:{\"name\":\"parsecdedup\"}": {
                                        ".": {},
                                        "f:args": {},
                                        "f:command": {},
                                        "f:image": {},
                                        "f:imagePullPolicy": {},
                                        "f:name": {},
                                        "f:resources": {},
                                        "f:terminationMessagePath": {},
                                        "f:terminationMessagePolicy": {}
                                    }
                                },
                                "f:dnsPolicy": {},
                                "f:enableServiceLinks": {},
                                "f:nodeSelector": {
                                    ".": {},
                                    "f:cca-project-nodetype": {}
                                },
                                "f:restartPolicy": {},
                                "f:schedulerName": {},
                                "f:securityContext": {},
                                "f:terminationGracePeriodSeconds": {}
                            }
                        },
                        "manager": "kube-controller-manager",
                        "operation": "Update",
                        "time": "2022-05-16T22:13:21Z"
                    },
                    {
                        "apiVersion": "v1",
                        "fieldsType": "FieldsV1",
                        "fieldsV1": {
                            "f:status": {
                                "f:conditions": {
                                    "k:{\"type\":\"ContainersReady\"}": {
                                        ".": {},
                                        "f:lastProbeTime": {},
                                        "f:lastTransitionTime": {},
                                        "f:reason": {},
                                        "f:status": {},
                                        "f:type": {}
                                    },
                                    "k:{\"type\":\"Initialized\"}": {
                                        ".": {},
                                        "f:lastProbeTime": {},
                                        "f:lastTransitionTime": {},
                                        "f:reason": {},
                                        "f:status": {},
                                        "f:type": {}
                                    },
                                    "k:{\"type\":\"Ready\"}": {
                                        ".": {},
                                        "f:lastProbeTime": {},
                                        "f:lastTransitionTime": {},
                                        "f:reason": {},
                                        "f:status": {},
                                        "f:type": {}
                                    }
                                },
                                "f:containerStatuses": {},
                                "f:hostIP": {},
                                "f:phase": {},
                                "f:podIP": {},
                                "f:podIPs": {
                                    ".": {},
                                    "k:{\"ip\":\"100.96.5.13\"}": {
                                        ".": {},
                                        "f:ip": {}
                                    }
                                },
                                "f:startTime": {}
                            }
                        },
                        "manager": "kubelet",
                        "operation": "Update",
                        "time": "2022-05-16T22:13:55Z"
                    }
                ],
                "name": "parsec-dedup-jf2xf",
                "namespace": "default",
                "ownerReferences": [
                    {
                        "apiVersion": "batch/v1",
                        "blockOwnerDeletion": true,
                        "controller": true,
                        "kind": "Job",
                        "name": "parsec-dedup",
                        "uid": "2a900972-37ae-49e2-a7be-f1d9edbda185"
                    }
                ],
                "resourceVersion": "10784",
                "selfLink": "/api/v1/namespaces/default/pods/parsec-dedup-jf2xf",
                "uid": "232a6098-9c0e-4dff-906a-5fedb64124d6"
            },
            "spec": {
                "containers": [
                    {
                        "args": [
                            "-c",
                            "taskset -c 0-3 ./bin/parsecmgmt -a run -p dedup -i native -n 3"
                        ],
                        "command": [
                            "/bin/sh"
                        ],
                        "image": "anakli/parsec:dedup-native-reduced",
                        "imagePullPolicy": "Always",
                        "name": "parsecdedup",
                        "resources": {
                            "requests": {
                                "cpu": "100m"
                            }
                        },
                        "terminationMessagePath": "/dev/termination-log",
                        "terminationMessagePolicy": "File",
                        "volumeMounts": [
                            {
                                "mountPath": "/var/run/secrets/kubernetes.io/serviceaccount",
                                "name": "default-token-qxwdw",
                                "readOnly": true
                            }
                        ]
                    }
                ],
                "dnsPolicy": "ClusterFirst",
                "enableServiceLinks": true,
                "nodeName": "node-b-4core-fcvz",
                "nodeSelector": {
                    "cca-project-nodetype": "node-b-4core"
                },
                "preemptionPolicy": "PreemptLowerPriority",
                "priority": 0,
                "restartPolicy": "Never",
                "schedulerName": "default-scheduler",
                "securityContext": {},
                "serviceAccount": "default",
                "serviceAccountName": "default",
                "terminationGracePeriodSeconds": 30,
                "tolerations": [
                    {
                        "effect": "NoExecute",
                        "key": "node.kubernetes.io/not-ready",
                        "operator": "Exists",
                        "tolerationSeconds": 300
                    },
                    {
                        "effect": "NoExecute",
                        "key": "node.kubernetes.io/unreachable",
                        "operator": "Exists",
                        "tolerationSeconds": 300
                    }
                ],
                "volumes": [
                    {
                        "name": "default-token-qxwdw",
                        "secret": {
                            "defaultMode": 420,
                            "secretName": "default-token-qxwdw"
                        }
                    }
                ]
            },
            "status": {
                "conditions": [
                    {
                        "lastProbeTime": null,
                        "lastTransitionTime": "2022-05-16T22:13:21Z",
                        "reason": "PodCompleted",
                        "status": "True",
                        "type": "Initialized"
                    },
                    {
                        "lastProbeTime": null,
                        "lastTransitionTime": "2022-05-16T22:13:55Z",
                        "reason": "PodCompleted",
                        "status": "False",
                        "type": "Ready"
                    },
                    {
                        "lastProbeTime": null,
                        "lastTransitionTime": "2022-05-16T22:13:55Z",
                        "reason": "PodCompleted",
                        "status": "False",
                        "type": "ContainersReady"
                    },
                    {
                        "lastProbeTime": null,
                        "lastTransitionTime": "2022-05-16T22:13:21Z",
                        "status": "True",
                        "type": "PodScheduled"
                    }
                ],
                "containerStatuses": [
                    {
                        "containerID": "docker://cd4235d909b3d1024425e68dcb04094ba913f6588b5f4059a986a81189df016e",
                        "image": "anakli/parsec:dedup-native-reduced",
                        "imageID": "docker-pullable://anakli/parsec@sha256:b61aef773919dce3e24284af9e052f3bdddcf1ed4b4e00961ff9ee0b08131e5d",
                        "lastState": {},
                        "name": "parsecdedup",
                        "ready": false,
                        "restartCount": 0,
                        "started": false,
                        "state": {
                            "terminated": {
                                "containerID": "docker://cd4235d909b3d1024425e68dcb04094ba913f6588b5f4059a986a81189df016e",
                                "exitCode": 0,
                                "finishedAt": "2022-05-16T22:13:46Z",
                                "reason": "Completed",
                                "startedAt": "2022-05-16T22:13:23Z"
                            }
                        }
                    }
                ],
                "hostIP": "10.156.15.230",
                "phase": "Succeeded",
                "podIP": "100.96.5.13",
                "podIPs": [
                    {
                        "ip": "100.96.5.13"
                    }
                ],
                "qosClass": "Burstable",
                "startTime": "2022-05-16T22:13:21Z"
            }
        },
        {
            "apiVersion": "v1",
            "kind": "Pod",
            "metadata": {
                "annotations": {
                    "kubernetes.io/limit-ranger": "LimitRanger plugin set: cpu request for container parsecferret"
                },
                "creationTimestamp": "2022-05-16T22:08:25Z",
                "generateName": "parsec-ferret-",
                "labels": {
                    "controller-uid": "b60652e9-5763-43fe-aa90-84ee575b82c5",
                    "job-name": "parsec-ferret"
                },
                "managedFields": [
                    {
                        "apiVersion": "v1",
                        "fieldsType": "FieldsV1",
                        "fieldsV1": {
                            "f:metadata": {
                                "f:generateName": {},
                                "f:labels": {
                                    ".": {},
                                    "f:controller-uid": {},
                                    "f:job-name": {}
                                },
                                "f:ownerReferences": {
                                    ".": {},
                                    "k:{\"uid\":\"b60652e9-5763-43fe-aa90-84ee575b82c5\"}": {
                                        ".": {},
                                        "f:apiVersion": {},
                                        "f:blockOwnerDeletion": {},
                                        "f:controller": {},
                                        "f:kind": {},
                                        "f:name": {},
                                        "f:uid": {}
                                    }
                                }
                            },
                            "f:spec": {
                                "f:containers": {
                                    "k:{\"name\":\"parsecferret\"}": {
                                        ".": {},
                                        "f:args": {},
                                        "f:command": {},
                                        "f:image": {},
                                        "f:imagePullPolicy": {},
                                        "f:name": {},
                                        "f:resources": {},
                                        "f:terminationMessagePath": {},
                                        "f:terminationMessagePolicy": {}
                                    }
                                },
                                "f:dnsPolicy": {},
                                "f:enableServiceLinks": {},
                                "f:nodeSelector": {
                                    ".": {},
                                    "f:cca-project-nodetype": {}
                                },
                                "f:restartPolicy": {},
                                "f:schedulerName": {},
                                "f:securityContext": {},
                                "f:terminationGracePeriodSeconds": {}
                            }
                        },
                        "manager": "kube-controller-manager",
                        "operation": "Update",
                        "time": "2022-05-16T22:08:25Z"
                    },
                    {
                        "apiVersion": "v1",
                        "fieldsType": "FieldsV1",
                        "fieldsV1": {
                            "f:status": {
                                "f:conditions": {
                                    "k:{\"type\":\"ContainersReady\"}": {
                                        ".": {},
                                        "f:lastProbeTime": {},
                                        "f:lastTransitionTime": {},
                                        "f:reason": {},
                                        "f:status": {},
                                        "f:type": {}
                                    },
                                    "k:{\"type\":\"Initialized\"}": {
                                        ".": {},
                                        "f:lastProbeTime": {},
                                        "f:lastTransitionTime": {},
                                        "f:reason": {},
                                        "f:status": {},
                                        "f:type": {}
                                    },
                                    "k:{\"type\":\"Ready\"}": {
                                        ".": {},
                                        "f:lastProbeTime": {},
                                        "f:lastTransitionTime": {},
                                        "f:reason": {},
                                        "f:status": {},
                                        "f:type": {}
                                    }
                                },
                                "f:containerStatuses": {},
                                "f:hostIP": {},
                                "f:phase": {},
                                "f:podIP": {},
                                "f:podIPs": {
                                    ".": {},
                                    "k:{\"ip\":\"100.96.5.12\"}": {
                                        ".": {},
                                        "f:ip": {}
                                    }
                                },
                                "f:startTime": {}
                            }
                        },
                        "manager": "kubelet",
                        "operation": "Update",
                        "time": "2022-05-16T22:13:18Z"
                    }
                ],
                "name": "parsec-ferret-qcbw2",
                "namespace": "default",
                "ownerReferences": [
                    {
                        "apiVersion": "batch/v1",
                        "blockOwnerDeletion": true,
                        "controller": true,
                        "kind": "Job",
                        "name": "parsec-ferret",
                        "uid": "b60652e9-5763-43fe-aa90-84ee575b82c5"
                    }
                ],
                "resourceVersion": "10650",
                "selfLink": "/api/v1/namespaces/default/pods/parsec-ferret-qcbw2",
                "uid": "49e6524c-1339-474b-b755-7b085f661a54"
            },
            "spec": {
                "containers": [
                    {
                        "args": [
                            "-c",
                            "taskset -c 0-3 ./bin/parsecmgmt -a run -p ferret -i native -n 4"
                        ],
                        "command": [
                            "/bin/sh"
                        ],
                        "image": "anakli/parsec:ferret-native-reduced",
                        "imagePullPolicy": "Always",
                        "name": "parsecferret",
                        "resources": {
                            "requests": {
                                "cpu": "100m"
                            }
                        },
                        "terminationMessagePath": "/dev/termination-log",
                        "terminationMessagePolicy": "File",
                        "volumeMounts": [
                            {
                                "mountPath": "/var/run/secrets/kubernetes.io/serviceaccount",
                                "name": "default-token-qxwdw",
                                "readOnly": true
                            }
                        ]
                    }
                ],
                "dnsPolicy": "ClusterFirst",
                "enableServiceLinks": true,
                "nodeName": "node-b-4core-fcvz",
                "nodeSelector": {
                    "cca-project-nodetype": "node-b-4core"
                },
                "preemptionPolicy": "PreemptLowerPriority",
                "priority": 0,
                "restartPolicy": "Never",
                "schedulerName": "default-scheduler",
                "securityContext": {},
                "serviceAccount": "default",
                "serviceAccountName": "default",
                "terminationGracePeriodSeconds": 30,
                "tolerations": [
                    {
                        "effect": "NoExecute",
                        "key": "node.kubernetes.io/not-ready",
                        "operator": "Exists",
                        "tolerationSeconds": 300
                    },
                    {
                        "effect": "NoExecute",
                        "key": "node.kubernetes.io/unreachable",
                        "operator": "Exists",
                        "tolerationSeconds": 300
                    }
                ],
                "volumes": [
                    {
                        "name": "default-token-qxwdw",
                        "secret": {
                            "defaultMode": 420,
                            "secretName": "default-token-qxwdw"
                        }
                    }
                ]
            },
            "status": {
                "conditions": [
                    {
                        "lastProbeTime": null,
                        "lastTransitionTime": "2022-05-16T22:08:25Z",
                        "reason": "PodCompleted",
                        "status": "True",
                        "type": "Initialized"
                    },
                    {
                        "lastProbeTime": null,
                        "lastTransitionTime": "2022-05-16T22:13:18Z",
                        "reason": "PodCompleted",
                        "status": "False",
                        "type": "Ready"
                    },
                    {
                        "lastProbeTime": null,
                        "lastTransitionTime": "2022-05-16T22:13:18Z",
                        "reason": "PodCompleted",
                        "status": "False",
                        "type": "ContainersReady"
                    },
                    {
                        "lastProbeTime": null,
                        "lastTransitionTime": "2022-05-16T22:08:25Z",
                        "status": "True",
                        "type": "PodScheduled"
                    }
                ],
                "containerStatuses": [
                    {
                        "containerID": "docker://37d8e8ef32cd1331a96d6b2016663417ff1c6b78e77a9199a91bdd0793d08cf0",
                        "image": "anakli/parsec:ferret-native-reduced",
                        "imageID": "docker-pullable://anakli/parsec@sha256:9328e510def0b53cca272134901b0147b7895d029d37d99c7aba66d172d3050c",
                        "lastState": {},
                        "name": "parsecferret",
                        "ready": false,
                        "restartCount": 0,
                        "started": false,
                        "state": {
                            "terminated": {
                                "containerID": "docker://37d8e8ef32cd1331a96d6b2016663417ff1c6b78e77a9199a91bdd0793d08cf0",
                                "exitCode": 0,
                                "finishedAt": "2022-05-16T22:13:17Z",
                                "reason": "Completed",
                                "startedAt": "2022-05-16T22:08:27Z"
                            }
                        }
                    }
                ],
                "hostIP": "10.156.15.230",
                "phase": "Succeeded",
                "podIP": "100.96.5.12",
                "podIPs": [
                    {
                        "ip": "100.96.5.12"
                    }
                ],
                "qosClass": "Burstable",
                "startTime": "2022-05-16T22:08:25Z"
            }
        },
        {
            "apiVersion": "v1",
            "kind": "Pod",
            "metadata": {
                "creationTimestamp": "2022-05-16T22:08:24Z",
                "generateName": "parsec-freqmine-",
                "labels": {
                    "controller-uid": "f5d01e33-7612-4c6d-9611-b9f1de6501cf",
                    "job-name": "parsec-freqmine"
                },
                "managedFields": [
                    {
                        "apiVersion": "v1",
                        "fieldsType": "FieldsV1",
                        "fieldsV1": {
                            "f:metadata": {
                                "f:generateName": {},
                                "f:labels": {
                                    ".": {},
                                    "f:controller-uid": {},
                                    "f:job-name": {}
                                },
                                "f:ownerReferences": {
                                    ".": {},
                                    "k:{\"uid\":\"f5d01e33-7612-4c6d-9611-b9f1de6501cf\"}": {
                                        ".": {},
                                        "f:apiVersion": {},
                                        "f:blockOwnerDeletion": {},
                                        "f:controller": {},
                                        "f:kind": {},
                                        "f:name": {},
                                        "f:uid": {}
                                    }
                                }
                            },
                            "f:spec": {
                                "f:containers": {
                                    "k:{\"name\":\"parsecfreqmine\"}": {
                                        ".": {},
                                        "f:args": {},
                                        "f:command": {},
                                        "f:image": {},
                                        "f:imagePullPolicy": {},
                                        "f:name": {},
                                        "f:resources": {
                                            ".": {},
                                            "f:limits": {
                                                ".": {},
                                                "f:cpu": {}
                                            },
                                            "f:requests": {
                                                ".": {},
                                                "f:cpu": {}
                                            }
                                        },
                                        "f:terminationMessagePath": {},
                                        "f:terminationMessagePolicy": {}
                                    }
                                },
                                "f:dnsPolicy": {},
                                "f:enableServiceLinks": {},
                                "f:nodeSelector": {
                                    ".": {},
                                    "f:cca-project-nodetype": {}
                                },
                                "f:restartPolicy": {},
                                "f:schedulerName": {},
                                "f:securityContext": {},
                                "f:terminationGracePeriodSeconds": {}
                            }
                        },
                        "manager": "kube-controller-manager",
                        "operation": "Update",
                        "time": "2022-05-16T22:08:24Z"
                    },
                    {
                        "apiVersion": "v1",
                        "fieldsType": "FieldsV1",
                        "fieldsV1": {
                            "f:status": {
                                "f:conditions": {
                                    "k:{\"type\":\"ContainersReady\"}": {
                                        ".": {},
                                        "f:lastProbeTime": {},
                                        "f:lastTransitionTime": {},
                                        "f:reason": {},
                                        "f:status": {},
                                        "f:type": {}
                                    },
                                    "k:{\"type\":\"Initialized\"}": {
                                        ".": {},
                                        "f:lastProbeTime": {},
                                        "f:lastTransitionTime": {},
                                        "f:reason": {},
                                        "f:status": {},
                                        "f:type": {}
                                    },
                                    "k:{\"type\":\"Ready\"}": {
                                        ".": {},
                                        "f:lastProbeTime": {},
                                        "f:lastTransitionTime": {},
                                        "f:reason": {},
                                        "f:status": {},
                                        "f:type": {}
                                    }
                                },
                                "f:containerStatuses": {},
                                "f:hostIP": {},
                                "f:phase": {},
                                "f:podIP": {},
                                "f:podIPs": {
                                    ".": {},
                                    "k:{\"ip\":\"100.96.3.20\"}": {
                                        ".": {},
                                        "f:ip": {}
                                    }
                                },
                                "f:startTime": {}
                            }
                        },
                        "manager": "kubelet",
                        "operation": "Update",
                        "time": "2022-05-16T22:10:21Z"
                    }
                ],
                "name": "parsec-freqmine-5z7m9",
                "namespace": "default",
                "ownerReferences": [
                    {
                        "apiVersion": "batch/v1",
                        "blockOwnerDeletion": true,
                        "controller": true,
                        "kind": "Job",
                        "name": "parsec-freqmine",
                        "uid": "f5d01e33-7612-4c6d-9611-b9f1de6501cf"
                    }
                ],
                "resourceVersion": "10045",
                "selfLink": "/api/v1/namespaces/default/pods/parsec-freqmine-5z7m9",
                "uid": "641e9354-d1f0-4bb6-87d8-591fd9125596"
            },
            "spec": {
                "containers": [
                    {
                        "args": [
                            "-c",
                            "taskset -c 0-5 ./bin/parsecmgmt -a run -p freqmine -i native -n 6"
                        ],
                        "command": [
                            "/bin/sh"
                        ],
                        "image": "anakli/parsec:freqmine-native-reduced",
                        "imagePullPolicy": "Always",
                        "name": "parsecfreqmine",
                        "resources": {
                            "limits": {
                                "cpu": "6"
                            },
                            "requests": {
                                "cpu": "6"
                            }
                        },
                        "terminationMessagePath": "/dev/termination-log",
                        "terminationMessagePolicy": "File",
                        "volumeMounts": [
                            {
                                "mountPath": "/var/run/secrets/kubernetes.io/serviceaccount",
                                "name": "default-token-qxwdw",
                                "readOnly": true
                            }
                        ]
                    }
                ],
                "dnsPolicy": "ClusterFirst",
                "enableServiceLinks": true,
                "nodeName": "node-c-8core-g1vx",
                "nodeSelector": {
                    "cca-project-nodetype": "node-c-8core"
                },
                "preemptionPolicy": "PreemptLowerPriority",
                "priority": 0,
                "restartPolicy": "Never",
                "schedulerName": "default-scheduler",
                "securityContext": {},
                "serviceAccount": "default",
                "serviceAccountName": "default",
                "terminationGracePeriodSeconds": 30,
                "tolerations": [
                    {
                        "effect": "NoExecute",
                        "key": "node.kubernetes.io/not-ready",
                        "operator": "Exists",
                        "tolerationSeconds": 300
                    },
                    {
                        "effect": "NoExecute",
                        "key": "node.kubernetes.io/unreachable",
                        "operator": "Exists",
                        "tolerationSeconds": 300
                    }
                ],
                "volumes": [
                    {
                        "name": "default-token-qxwdw",
                        "secret": {
                            "defaultMode": 420,
                            "secretName": "default-token-qxwdw"
                        }
                    }
                ]
            },
            "status": {
                "conditions": [
                    {
                        "lastProbeTime": null,
                        "lastTransitionTime": "2022-05-16T22:08:24Z",
                        "reason": "PodCompleted",
                        "status": "True",
                        "type": "Initialized"
                    },
                    {
                        "lastProbeTime": null,
                        "lastTransitionTime": "2022-05-16T22:10:21Z",
                        "reason": "PodCompleted",
                        "status": "False",
                        "type": "Ready"
                    },
                    {
                        "lastProbeTime": null,
                        "lastTransitionTime": "2022-05-16T22:10:21Z",
                        "reason": "PodCompleted",
                        "status": "False",
                        "type": "ContainersReady"
                    },
                    {
                        "lastProbeTime": null,
                        "lastTransitionTime": "2022-05-16T22:08:24Z",
                        "status": "True",
                        "type": "PodScheduled"
                    }
                ],
                "containerStatuses": [
                    {
                        "containerID": "docker://f23b110d95a2f501fc09cf50bafa08bbdbfc5b99ab8beeaca7c136e971f3d4a2",
                        "image": "anakli/parsec:freqmine-native-reduced",
                        "imageID": "docker-pullable://anakli/parsec@sha256:0bfc97728dbec5b85b0436a164c824a0bbe0105428e4423dd03b7408f14c7d6b",
                        "lastState": {},
                        "name": "parsecfreqmine",
                        "ready": false,
                        "restartCount": 0,
                        "started": false,
                        "state": {
                            "terminated": {
                                "containerID": "docker://f23b110d95a2f501fc09cf50bafa08bbdbfc5b99ab8beeaca7c136e971f3d4a2",
                                "exitCode": 0,
                                "finishedAt": "2022-05-16T22:10:20Z",
                                "reason": "Completed",
                                "startedAt": "2022-05-16T22:08:26Z"
                            }
                        }
                    }
                ],
                "hostIP": "10.156.15.227",
                "phase": "Succeeded",
                "podIP": "100.96.3.20",
                "podIPs": [
                    {
                        "ip": "100.96.3.20"
                    }
                ],
                "qosClass": "Burstable",
                "startTime": "2022-05-16T22:08:24Z"
            }
        },
        {
            "apiVersion": "v1",
            "kind": "Pod",
            "metadata": {
                "creationTimestamp": "2022-05-16T22:08:25Z",
                "generateName": "parsec-splash2x-fft-",
                "labels": {
                    "controller-uid": "6765a01a-c1e3-4869-872c-e8047df50457",
                    "job-name": "parsec-splash2x-fft"
                },
                "managedFields": [
                    {
                        "apiVersion": "v1",
                        "fieldsType": "FieldsV1",
                        "fieldsV1": {
                            "f:metadata": {
                                "f:generateName": {},
                                "f:labels": {
                                    ".": {},
                                    "f:controller-uid": {},
                                    "f:job-name": {}
                                },
                                "f:ownerReferences": {
                                    ".": {},
                                    "k:{\"uid\":\"6765a01a-c1e3-4869-872c-e8047df50457\"}": {
                                        ".": {},
                                        "f:apiVersion": {},
                                        "f:blockOwnerDeletion": {},
                                        "f:controller": {},
                                        "f:kind": {},
                                        "f:name": {},
                                        "f:uid": {}
                                    }
                                }
                            },
                            "f:spec": {
                                "f:containers": {
                                    "k:{\"name\":\"parsec-splash2x-fft\"}": {
                                        ".": {},
                                        "f:args": {},
                                        "f:command": {},
                                        "f:image": {},
                                        "f:imagePullPolicy": {},
                                        "f:name": {},
                                        "f:resources": {
                                            ".": {},
                                            "f:limits": {
                                                ".": {},
                                                "f:cpu": {}
                                            },
                                            "f:requests": {
                                                ".": {},
                                                "f:cpu": {}
                                            }
                                        },
                                        "f:terminationMessagePath": {},
                                        "f:terminationMessagePolicy": {}
                                    }
                                },
                                "f:dnsPolicy": {},
                                "f:enableServiceLinks": {},
                                "f:nodeSelector": {
                                    ".": {},
                                    "f:cca-project-nodetype": {}
                                },
                                "f:restartPolicy": {},
                                "f:schedulerName": {},
                                "f:securityContext": {},
                                "f:terminationGracePeriodSeconds": {}
                            }
                        },
                        "manager": "kube-controller-manager",
                        "operation": "Update",
                        "time": "2022-05-16T22:08:25Z"
                    },
                    {
                        "apiVersion": "v1",
                        "fieldsType": "FieldsV1",
                        "fieldsV1": {
                            "f:status": {
                                "f:conditions": {
                                    ".": {},
                                    "k:{\"type\":\"PodScheduled\"}": {
                                        ".": {},
                                        "f:lastProbeTime": {},
                                        "f:lastTransitionTime": {},
                                        "f:message": {},
                                        "f:reason": {},
                                        "f:status": {},
                                        "f:type": {}
                                    }
                                }
                            }
                        },
                        "manager": "kube-scheduler",
                        "operation": "Update",
                        "time": "2022-05-16T22:08:25Z"
                    },
                    {
                        "apiVersion": "v1",
                        "fieldsType": "FieldsV1",
                        "fieldsV1": {
                            "f:status": {
                                "f:conditions": {
                                    "k:{\"type\":\"ContainersReady\"}": {
                                        ".": {},
                                        "f:lastProbeTime": {},
                                        "f:lastTransitionTime": {},
                                        "f:reason": {},
                                        "f:status": {},
                                        "f:type": {}
                                    },
                                    "k:{\"type\":\"Initialized\"}": {
                                        ".": {},
                                        "f:lastProbeTime": {},
                                        "f:lastTransitionTime": {},
                                        "f:reason": {},
                                        "f:status": {},
                                        "f:type": {}
                                    },
                                    "k:{\"type\":\"Ready\"}": {
                                        ".": {},
                                        "f:lastProbeTime": {},
                                        "f:lastTransitionTime": {},
                                        "f:reason": {},
                                        "f:status": {},
                                        "f:type": {}
                                    }
                                },
                                "f:containerStatuses": {},
                                "f:hostIP": {},
                                "f:phase": {},
                                "f:podIP": {},
                                "f:podIPs": {
                                    ".": {},
                                    "k:{\"ip\":\"100.96.3.21\"}": {
                                        ".": {},
                                        "f:ip": {}
                                    }
                                },
                                "f:startTime": {}
                            }
                        },
                        "manager": "kubelet",
                        "operation": "Update",
                        "time": "2022-05-16T22:12:21Z"
                    }
                ],
                "name": "parsec-splash2x-fft-xmcz7",
                "namespace": "default",
                "ownerReferences": [
                    {
                        "apiVersion": "batch/v1",
                        "blockOwnerDeletion": true,
                        "controller": true,
                        "kind": "Job",
                        "name": "parsec-splash2x-fft",
                        "uid": "6765a01a-c1e3-4869-872c-e8047df50457"
                    }
                ],
                "resourceVersion": "10454",
                "selfLink": "/api/v1/namespaces/default/pods/parsec-splash2x-fft-xmcz7",
                "uid": "d9e621a3-ae7a-4bc3-9d32-75cf5183106c"
            },
            "spec": {
                "containers": [
                    {
                        "args": [
                            "-c",
                            "taskset -c 6-7 ./bin/parsecmgmt -a run -p splash2x.fft -i native -n 2"
                        ],
                        "command": [
                            "/bin/sh"
                        ],
                        "image": "anakli/parsec:splash2x-fft-native-reduced",
                        "imagePullPolicy": "Always",
                        "name": "parsec-splash2x-fft",
                        "resources": {
                            "limits": {
                                "cpu": "2"
                            },
                            "requests": {
                                "cpu": "2"
                            }
                        },
                        "terminationMessagePath": "/dev/termination-log",
                        "terminationMessagePolicy": "File",
                        "volumeMounts": [
                            {
                                "mountPath": "/var/run/secrets/kubernetes.io/serviceaccount",
                                "name": "default-token-qxwdw",
                                "readOnly": true
                            }
                        ]
                    }
                ],
                "dnsPolicy": "ClusterFirst",
                "enableServiceLinks": true,
                "nodeName": "node-c-8core-g1vx",
                "nodeSelector": {
                    "cca-project-nodetype": "node-c-8core"
                },
                "preemptionPolicy": "PreemptLowerPriority",
                "priority": 0,
                "restartPolicy": "Never",
                "schedulerName": "default-scheduler",
                "securityContext": {},
                "serviceAccount": "default",
                "serviceAccountName": "default",
                "terminationGracePeriodSeconds": 30,
                "tolerations": [
                    {
                        "effect": "NoExecute",
                        "key": "node.kubernetes.io/not-ready",
                        "operator": "Exists",
                        "tolerationSeconds": 300
                    },
                    {
                        "effect": "NoExecute",
                        "key": "node.kubernetes.io/unreachable",
                        "operator": "Exists",
                        "tolerationSeconds": 300
                    }
                ],
                "volumes": [
                    {
                        "name": "default-token-qxwdw",
                        "secret": {
                            "defaultMode": 420,
                            "secretName": "default-token-qxwdw"
                        }
                    }
                ]
            },
            "status": {
                "conditions": [
                    {
                        "lastProbeTime": null,
                        "lastTransitionTime": "2022-05-16T22:10:21Z",
                        "reason": "PodCompleted",
                        "status": "True",
                        "type": "Initialized"
                    },
                    {
                        "lastProbeTime": null,
                        "lastTransitionTime": "2022-05-16T22:12:21Z",
                        "reason": "PodCompleted",
                        "status": "False",
                        "type": "Ready"
                    },
                    {
                        "lastProbeTime": null,
                        "lastTransitionTime": "2022-05-16T22:12:21Z",
                        "reason": "PodCompleted",
                        "status": "False",
                        "type": "ContainersReady"
                    },
                    {
                        "lastProbeTime": null,
                        "lastTransitionTime": "2022-05-16T22:10:21Z",
                        "status": "True",
                        "type": "PodScheduled"
                    }
                ],
                "containerStatuses": [
                    {
                        "containerID": "docker://3a447bf8d8c582f86b8bc06c940a63c04829721c76f0ed39b57fd53dcb76870c",
                        "image": "anakli/parsec:splash2x-fft-native-reduced",
                        "imageID": "docker-pullable://anakli/parsec@sha256:b8b60f8dcfd7e9947911aa134de0a909d33679130f0013bcb4fea2db113ef151",
                        "lastState": {},
                        "name": "parsec-splash2x-fft",
                        "ready": false,
                        "restartCount": 0,
                        "started": false,
                        "state": {
                            "terminated": {
                                "containerID": "docker://3a447bf8d8c582f86b8bc06c940a63c04829721c76f0ed39b57fd53dcb76870c",
                                "exitCode": 0,
                                "finishedAt": "2022-05-16T22:12:20Z",
                                "reason": "Completed",
                                "startedAt": "2022-05-16T22:10:23Z"
                            }
                        }
                    }
                ],
                "hostIP": "10.156.15.227",
                "phase": "Succeeded",
                "podIP": "100.96.3.21",
                "podIPs": [
                    {
                        "ip": "100.96.3.21"
                    }
                ],
                "qosClass": "Burstable",
                "startTime": "2022-05-16T22:10:21Z"
            }
        },
        {
            "apiVersion": "v1",
            "kind": "Pod",
            "metadata": {
                "creationTimestamp": "2022-05-16T21:30:24Z",
                "labels": {
                    "name": "some-memcached"
                },
                "managedFields": [
                    {
                        "apiVersion": "v1",
                        "fieldsType": "FieldsV1",
                        "fieldsV1": {
                            "f:metadata": {
                                "f:labels": {
                                    ".": {},
                                    "f:name": {}
                                }
                            },
                            "f:spec": {
                                "f:containers": {
                                    "k:{\"name\":\"memcached\"}": {
                                        ".": {},
                                        "f:args": {},
                                        "f:command": {},
                                        "f:image": {},
                                        "f:imagePullPolicy": {},
                                        "f:name": {},
                                        "f:resources": {
                                            ".": {},
                                            "f:limits": {
                                                ".": {},
                                                "f:cpu": {}
                                            },
                                            "f:requests": {
                                                ".": {},
                                                "f:cpu": {}
                                            }
                                        },
                                        "f:terminationMessagePath": {},
                                        "f:terminationMessagePolicy": {}
                                    }
                                },
                                "f:dnsPolicy": {},
                                "f:enableServiceLinks": {},
                                "f:nodeSelector": {
                                    ".": {},
                                    "f:cca-project-nodetype": {}
                                },
                                "f:restartPolicy": {},
                                "f:schedulerName": {},
                                "f:securityContext": {},
                                "f:terminationGracePeriodSeconds": {}
                            }
                        },
                        "manager": "kubectl-create",
                        "operation": "Update",
                        "time": "2022-05-16T21:30:24Z"
                    },
                    {
                        "apiVersion": "v1",
                        "fieldsType": "FieldsV1",
                        "fieldsV1": {
                            "f:status": {
                                "f:conditions": {
                                    "k:{\"type\":\"ContainersReady\"}": {
                                        ".": {},
                                        "f:lastProbeTime": {},
                                        "f:lastTransitionTime": {},
                                        "f:status": {},
                                        "f:type": {}
                                    },
                                    "k:{\"type\":\"Initialized\"}": {
                                        ".": {},
                                        "f:lastProbeTime": {},
                                        "f:lastTransitionTime": {},
                                        "f:status": {},
                                        "f:type": {}
                                    },
                                    "k:{\"type\":\"Ready\"}": {
                                        ".": {},
                                        "f:lastProbeTime": {},
                                        "f:lastTransitionTime": {},
                                        "f:status": {},
                                        "f:type": {}
                                    }
                                },
                                "f:containerStatuses": {},
                                "f:hostIP": {},
                                "f:phase": {},
                                "f:podIP": {},
                                "f:podIPs": {
                                    ".": {},
                                    "k:{\"ip\":\"100.96.1.2\"}": {
                                        ".": {},
                                        "f:ip": {}
                                    }
                                },
                                "f:startTime": {}
                            }
                        },
                        "manager": "kubelet",
                        "operation": "Update",
                        "time": "2022-05-16T21:30:35Z"
                    }
                ],
                "name": "some-memcached",
                "namespace": "default",
                "resourceVersion": "1783",
                "selfLink": "/api/v1/namespaces/default/pods/some-memcached",
                "uid": "991ff695-b12c-469a-86b3-1448f0f916c2"
            },
            "spec": {
                "containers": [
                    {
                        "args": [
                            "-c",
                            "taskset -c 0 ./memcached -t 1 -u memcache"
                        ],
                        "command": [
                            "/bin/sh"
                        ],
                        "image": "anakli/memcached:t1",
                        "imagePullPolicy": "Always",
                        "name": "memcached",
                        "resources": {
                            "limits": {
                                "cpu": "1"
                            },
                            "requests": {
                                "cpu": "1"
                            }
                        },
                        "terminationMessagePath": "/dev/termination-log",
                        "terminationMessagePolicy": "File",
                        "volumeMounts": [
                            {
                                "mountPath": "/var/run/secrets/kubernetes.io/serviceaccount",
                                "name": "default-token-qxwdw",
                                "readOnly": true
                            }
                        ]
                    }
                ],
                "dnsPolicy": "ClusterFirst",
                "enableServiceLinks": true,
                "nodeName": "node-a-2core-9mtt",
                "nodeSelector": {
                    "cca-project-nodetype": "node-a-2core"
                },
                "preemptionPolicy": "PreemptLowerPriority",
                "priority": 0,
                "restartPolicy": "Always",
                "schedulerName": "default-scheduler",
                "securityContext": {},
                "serviceAccount": "default",
                "serviceAccountName": "default",
                "terminationGracePeriodSeconds": 30,
                "tolerations": [
                    {
                        "effect": "NoExecute",
                        "key": "node.kubernetes.io/not-ready",
                        "operator": "Exists",
                        "tolerationSeconds": 300
                    },
                    {
                        "effect": "NoExecute",
                        "key": "node.kubernetes.io/unreachable",
                        "operator": "Exists",
                        "tolerationSeconds": 300
                    }
                ],
                "volumes": [
                    {
                        "name": "default-token-qxwdw",
                        "secret": {
                            "defaultMode": 420,
                            "secretName": "default-token-qxwdw"
                        }
                    }
                ]
            },
            "status": {
                "conditions": [
                    {
                        "lastProbeTime": null,
                        "lastTransitionTime": "2022-05-16T21:30:24Z",
                        "status": "True",
                        "type": "Initialized"
                    },
                    {
                        "lastProbeTime": null,
                        "lastTransitionTime": "2022-05-16T21:30:35Z",
                        "status": "True",
                        "type": "Ready"
                    },
                    {
                        "lastProbeTime": null,
                        "lastTransitionTime": "2022-05-16T21:30:35Z",
                        "status": "True",
                        "type": "ContainersReady"
                    },
                    {
                        "lastProbeTime": null,
                        "lastTransitionTime": "2022-05-16T21:30:24Z",
                        "status": "True",
                        "type": "PodScheduled"
                    }
                ],
                "containerStatuses": [
                    {
                        "containerID": "docker://0b249872188c173c249ea5a57f8d959759113ffe08b5026fd2439eb837166560",
                        "image": "anakli/memcached:t1",
                        "imageID": "docker-pullable://anakli/memcached@sha256:04a3fa6ff86d7f3fcd0eb378e0f41fa3ba84b890d3a745fcea9704659d075b27",
                        "lastState": {},
                        "name": "memcached",
                        "ready": true,
                        "restartCount": 0,
                        "started": true,
                        "state": {
                            "running": {
                                "startedAt": "2022-05-16T21:30:35Z"
                            }
                        }
                    }
                ],
                "hostIP": "10.156.15.229",
                "phase": "Running",
                "podIP": "100.96.1.2",
                "podIPs": [
                    {
                        "ip": "100.96.1.2"
                    }
                ],
                "qosClass": "Burstable",
                "startTime": "2022-05-16T21:30:24Z"
            }
        }
    ],
    "kind": "List",
    "metadata": {
        "resourceVersion": "",
        "selfLink": ""
    }
}
